README.rst
setup.py
gspreadsheet/__init__.py
gspreadsheet/auth.py
gspreadsheet/gspreadsheet.py
gspreadsheet/tests.py
gspreadsheet/utils.py
gspreadsheet.egg-info/PKG-INFO
gspreadsheet.egg-info/SOURCES.txt
gspreadsheet.egg-info/dependency_links.txt
gspreadsheet.egg-info/requires.txt
gspreadsheet.egg-info/top_level.txt