Metadata-Version: 1.1
Name: gspreadsheet
Version: 0.4.0
Summary: A wrapper around a wrapper to get Google spreadsheets to look like DictReader
Home-page: https://github.com/texastribune/gspreadsheet
Author: Chris Chang
Author-email: cchang@texastribune.org
License: Apache Software License
Platform: UNKNOWN
Classifier: Development Status :: 4 - Beta
Classifier: Intended Audience :: Developers
Classifier: License :: OSI Approved :: Apache Software License
Classifier: Operating System :: OS Independent
Classifier: Programming Language :: Python
Classifier: Programming Language :: Python :: 2
Classifier: Programming Language :: Python :: 2.6
Classifier: Programming Language :: Python :: 2.7
